mcp_streamablehttp_proxy/__init__.py
mcp_streamablehttp_proxy/cli.py
mcp_streamablehttp_proxy/proxy.py
mcp_streamablehttp_proxy/py.typed
mcp_streamablehttp_proxy/server.py
mcp_streamablehttp_proxy-0.2.0.dist-info/METADATA
mcp_streamablehttp_proxy-0.2.0.dist-info/WHEEL
mcp_streamablehttp_proxy-0.2.0.dist-info/entry_points.txt
mcp_streamablehttp_proxy-0.2.0.dist-info/licenses/LICENSE
mcp_streamablehttp_proxy-0.2.0.dist-info/RECORD
