Metadata-Version: 2.4
Name: mcp-streamablehttp-proxy
Version: 0.2.0
Summary: A generic stdio-to-streamable-HTTP proxy for MCP (Model Context Protocol) servers
Project-URL: Homepage, https://github.com/atrawog/mcp-oauth-gateway/tree/main/mcp-streamablehttp-proxy
Project-URL: Repository, https://github.com/atrawog/mcp-oauth-gateway/tree/main/mcp-streamablehttp-proxy
Project-URL: Issues, https://github.com/atrawog/mcp-oauth-gateway/issues
Project-URL: Documentation, https://atrawog.github.io/mcp-oauth-gateway
Author: Andreas Trawoeger
License-Expression: Apache-2.0
License-File: LICENSE
Keywords: mcp,model-context-protocol,proxy,stdio,streamable-http
Classifier: Development Status :: 4 - Beta
Classifier: Intended Audience :: Developers
Classifier: Programming Language :: Python :: 3
Classifier: Programming Language :: Python :: 3.8
Classifier: Programming Language :: Python :: 3.9
Classifier: Programming Language :: Python :: 3.10
Classifier: Programming Language :: Python :: 3.11
Classifier: Programming Language :: Python :: 3.12
Classifier: Topic :: Internet :: WWW/HTTP
Classifier: Topic :: Software Development :: Libraries :: Python Modules
Requires-Python: >=3.8
Requires-Dist: fastapi>=0.100.0
Requires-Dist: httpx>=0.24.0
Requires-Dist: uvicorn>=0.23.0
Provides-Extra: dev
Requires-Dist: black>=23.0.0; extra == 'dev'
Requires-Dist: mypy>=1.0.0; extra == 'dev'
Requires-Dist: pytest-asyncio>=0.21.0; extra == 'dev'
Requires-Dist: pytest-cov>=4.0.0; extra == 'dev'
Requires-Dist: pytest>=7.0.0; extra == 'dev'
Requires-Dist: ruff>=0.1.0; extra == 'dev'
